<annotation>
	<folder></folder>
	<filename>20210907_153931_x264_mp4-312_jpg.rf.79cf84af063f87a6240d45a0c83764dd.jpg</filename>
	<path>20210907_153931_x264_mp4-312_jpg.rf.79cf84af063f87a6240d45a0c83764dd.jpg</path>
	<source>
		<database>roboflow.com</database>
	</source>
	<size>
		<width>640</width>
		<height>640</height>
		<depth>3</depth>
	</size>
	<segmented>0</segmented>
	<object>
		<name>Weeds</name>
		<pose>Unspecified</pose>
		<truncated>0</truncated>
		<difficult>0</difficult>
		<occluded>0</occluded>
		<bndbox>
			<xmin>86</xmin>
			<xmax>507</xmax>
			<ymin>103</ymin>
			<ymax>590</ymax>
		</bndbox>
	</object>
</annotation>
