<annotation>
	<folder></folder>
	<filename>20210907_153931_x264_mp4-1640_jpg.rf.bcf3d5a033f3c5cf8c9dfa15ddb3e1ad.jpg</filename>
	<path>20210907_153931_x264_mp4-1640_jpg.rf.bcf3d5a033f3c5cf8c9dfa15ddb3e1ad.jpg</path>
	<source>
		<database>roboflow.com</database>
	</source>
	<size>
		<width>640</width>
		<height>640</height>
		<depth>3</depth>
	</size>
	<segmented>0</segmented>
	<object>
		<name>Weeds</name>
		<pose>Unspecified</pose>
		<truncated>0</truncated>
		<difficult>0</difficult>
		<occluded>0</occluded>
		<bndbox>
			<xmin>1</xmin>
			<xmax>436</xmax>
			<ymin>388</ymin>
			<ymax>639</ymax>
		</bndbox>
	</object>
	<object>
		<name>Weeds</name>
		<pose>Unspecified</pose>
		<truncated>0</truncated>
		<difficult>0</difficult>
		<occluded>0</occluded>
		<bndbox>
			<xmin>100</xmin>
			<xmax>517</xmax>
			<ymin>43</ymin>
			<ymax>414</ymax>
		</bndbox>
	</object>
</annotation>
